fcsapi_rest-4.0.0.dist-info/licenses/LICENSE
src/__init__.py
src/fcs_api.py
src/fcs_config.py
src/fcs_crypto.py
src/fcs_forex.py
src/fcs_stock.py
fcsapi_rest-4.0.0.dist-info/METADATA
fcsapi_rest-4.0.0.dist-info/WHEEL
fcsapi_rest-4.0.0.dist-info/top_level.txt
fcsapi_rest-4.0.0.dist-info/RECORD
