Metadata-Version: 2.4
Name: fcsapi-rest
Version: 4.0.0
Summary: Python REST API client for Forex, Cryptocurrency, and Stock market data from FCS API
Author-email: FCS API <support@fcsapi.com>
License: MIT
Project-URL: Homepage, https://github.com/fcsapi/rest-api-python
Project-URL: Documentation, https://fcsapi.com/document/forex-api
Project-URL: Repository, https://github.com/fcsapi/rest-api-python
Project-URL: Issues, https://github.com/fcsapi/rest-api-python/issues
Keywords: fcs,fcsapi,forex,cryptocurrency,crypto,stock,rest-api,market-data,trading,currency,exchange-rates,bitcoin,ethereum
Classifier: Development Status :: 5 - Production/Stable
Classifier: Intended Audience :: Developers
Classifier: Intended Audience :: Financial and Insurance Industry
Classifier: License :: OSI Approved :: MIT License
Classifier: Operating System :: OS Independent
Classifier: Programming Language :: Python :: 3
Classifier: Programming Language :: Python :: 3.7
Classifier: Programming Language :: Python :: 3.8
Classifier: Programming Language :: Python :: 3.9
Classifier: Programming Language :: Python :: 3.10
Classifier: Programming Language :: Python :: 3.11
Classifier: Programming Language :: Python :: 3.12
Classifier: Topic :: Office/Business :: Financial
Classifier: Topic :: Office/Business :: Financial :: Investment
Classifier: Topic :: Software Development :: Libraries :: Python Modules
Requires-Python: >=3.7
License-File: LICENSE
Requires-Dist: requests>=2.25.0
Provides-Extra: dev
Requires-Dist: pytest>=6.0; extra == "dev"
Requires-Dist: pytest-cov>=2.0; extra == "dev"
Dynamic: license-file
